GmGM/GmGM.py
GmGM/__init__.py
GmGM/dataset.py
GmGM/typing.py
GmGM/core/__init__.py
GmGM/core/core.py
GmGM/core/numbafied.py
GmGM/core/preprocessing.py
GmGM/core/presparse_methods.py
GmGM/core/subdivision.py
GmGM/extras/prior.py
GmGM/extras/regularizers.py
GmGM/synthetic/__init__.py
GmGM/synthetic/generate_data.py
GmGM/synthetic/validation.py
gmgm-0.5.6.dist-info/METADATA
gmgm-0.5.6.dist-info/WHEEL
gmgm-0.5.6.dist-info/licenses/LICENSE
gmgm-0.5.6.dist-info/RECORD
