Metadata-Version: 2.4
Name: GmGM
Version: 0.5.6
Summary: An implementation of the Gaussian multi-Graphical Model
Project-URL: Homepage, https://github.com/BaileyAndrew/GmGM-python
Project-URL: Bug Tracker, https://github.com/BaileyAndrew/GmGM-python/issues
Author-email: Bailey Andrew <sceba@leeds.ac.uk>
License: MIT License
License-File: LICENSE
Classifier: License :: OSI Approved :: MIT License
Classifier: Operating System :: OS Independent
Classifier: Programming Language :: Python :: 3
Classifier: Programming Language :: Python :: 3.9
Classifier: Programming Language :: Python :: 3.10
Classifier: Programming Language :: Python :: 3.11
Requires-Python: <3.13,>=3.9
Requires-Dist: dask>=2022.03
Requires-Dist: numba>=0.57
Requires-Dist: numpy>=1.23
Requires-Dist: scipy>=1.11
Provides-Extra: anndata
Requires-Dist: anndata; extra == 'anndata'
Provides-Extra: mudata
Requires-Dist: mudata; extra == 'mudata'
